{"UhIfys9O+xRs7pGf1kET+Q==":"mbr-2000x1333.jpg","0En7IVtv5szWbK8OLYnEEA==":"mbr-1-2000x1333.jpg","Dw/MbiQYMm2hmC5uiU7J/Q==":"mbr-2-2000x1333.jpg","djZOc0QjB6hL5QRQwqNNhA==":"1-2000x1500.jpg","QqI1k6HG34K52AitnupALA==":"2-2000x3330.jpg","GFvcn9ZNeBo9jSOmdBXq9w==":"3-2000x1125.jpg","Mh5RBeKR+JNYOtZHSB1GAw==":"4-2000x1125.jpg","Y+0QrAdW1cjHrSWp2j+1kw==":"5-2000x1125.jpg","FpncWdQN5pR1ujHIF2lZHg==":"6-2000x1125.jpg","EWzcQIdZt05m7lRjGVycNw==":"7-2000x1125.jpg","IJE+C9WKW3Rt3FS69pLocg==":"8-2000x1125.jpg","lAh9lfBa3PYQD7fvS6/WiA==":"asdasdsdf@0,3x-2000x1086.png","VlVpyECQzNRsrCceMg+HKA==":"asdasdsdf@2x-2000x1088.png","TXDz8XnP5yYjFkMWnnWjLg==":"google-classroom-2000x978.jpg","BJdJP0CbskYCzP2F8Rvoig==":"intergrate-1400x613.png","ueSQUf5tojUkC8SboThGMA==":"screenshot_20170731-600x1067.png","sLYJUg6/14hIIiR+Iyzkjg==":"screenshot_20170731-1-600x1067.png","kvCI7Q4wgpdJzqFQro92Ng==":"screenshot_20170731-2-600x1067.png","h+4/NnPflM6Gy6GK11FuKA==":"screenshot_20170731-3-600x1067.png","hBmeoSZFbyTDt2aU8b2XPA==":"screenshot_20170731-4-600x1067.png","O2JYMXrwH93U6pTA9Yueyw==":"screenshot_20170731-5-600x1067.png","9oVTMpYjQaXKX5W2kijW7A==":"mbr-2000x1500.jpg","ugkeDgK3rJKDEUqG40KfTQ==":"mbr-3-2000x1333.jpg","HtUswqfZa3NfrnEWCOjBag==":"mbr-4-2000x1333.jpg","TFuu+1f/gYjyFbBXkVCdTw==":"mbr-1-2000x1500.jpg","CepEqm5fzH7A0GcOh/quMw==":"mbr-5-2000x1333.jpg","5XURlzhVLMaDzaH20ls2pA==":"mbr-2000x1330.jpg"}